shrug_viz
