Metadata-Version: 1.0
Name: shrug-viz
Version: 0.1.5
Summary: Choropleth visualization for SHRUG data platform (SAMOSA version)
Home-page: UNKNOWN
Author: Kashmira L, Maithili K, Vibhuti D, Pradnya K
Author-email: kashmira.lodha@cumminscollege.in, pradnya.kanale@cumminscollege.in, vibhuti.dhande@cumminscollege.in, maithili.karlekar@cumminscollege.in
License: UNKNOWN
Platform: UNKNOWN
